Metadata-Version: 2.1
Name: casbin-async-postgresql-watcher
Version: 1.0.0
Summary: Async casbin role watcher to be used for monitoring updates to policies for PyCasbin
Author-email: hsluoyz <hsluoyz@gmail.com>
License: Apache 2.0
Project-URL: Home-page, https://github.com/pycasbin/async-postgres-watcher
Classifier: Programming Language :: Python :: 3.9
Classifier: Programming Language :: Python :: 3.10
Classifier: Programming Language :: Python :: 3.11
Classifier: Programming Language :: Python :: 3.12
Classifier: License :: OSI Approved :: Apache Software License
Classifier: Operating System :: OS Independent
Requires-Python: >=3.5
License-File: LICENSE
Requires-Dist: async-timeout ==4.0.3
Requires-Dist: asyncpg ==0.29.0
Requires-Dist: casbin ==1.36.0
Requires-Dist: simpleeval ==0.9.13
